ScheMatch-0.22.data/scripts/scr
schematch/__init__.py
schematch/match.py
ScheMatch-0.22.dist-info/METADATA
ScheMatch-0.22.dist-info/WHEEL
ScheMatch-0.22.dist-info/top_level.txt
ScheMatch-0.22.dist-info/RECORD
