Metadata-Version: 2.1
Name: ScheMatch
Version: 0.22
Summary: Basic dictionary schema checker
Home-page: https://github.com/sumitmukhija/ScheMatch
Author: Sumit Mukhija
Author-email: sumukhija@gmail.com
License: UNKNOWN
Platform: UNKNOWN
Classifier: Programming Language :: Python :: 3
Classifier: License :: OSI Approved :: MIT License
Classifier: Operating System :: OS Independent
